cfs.py
crypto.py
model.py
pycolonies.py
pycolonies-1.0.25.dist-info/LICENSE
pycolonies-1.0.25.dist-info/METADATA
pycolonies-1.0.25.dist-info/WHEEL
pycolonies-1.0.25.dist-info/top_level.txt
pycolonies-1.0.25.dist-info/RECORD
