Metadata-Version: 2.1
Name: pycolonies
Version: 1.0.25
Summary: Colonies Python SDK
Home-page: https://github.com/colonyos/pycolonies
Author: Johan Kristiansson
Author-email: johan.kristiansson@ri.se
Classifier: Programming Language :: Python :: 3
Classifier: License :: OSI Approved :: MIT License
Classifier: Operating System :: OS Independent
License-File: LICENSE
Requires-Dist: boto3 (>=1.34.136)
Requires-Dist: pydantic (>=2.6.4)
Requires-Dist: requests (>=2.27.1)
Requires-Dist: websocket-client (>=1.3.1)
